tessera_sdk/__init__.py
tessera_sdk/client.py
tessera_sdk/http.py
tessera_sdk/models.py
tessera_sdk/resources.py
tessera_sdk-0.1.5.dist-info/METADATA
tessera_sdk-0.1.5.dist-info/WHEEL
tessera_sdk-0.1.5.dist-info/licenses/LICENSE
tessera_sdk-0.1.5.dist-info/RECORD
