Metadata-Version: 2.4
Name: tessera-sdk
Version: 0.1.5
Summary: Python SDK for Tessera - Data contract coordination for warehouses
Project-URL: Homepage, https://github.com/ashita-ai/tessera-python
Project-URL: Documentation, https://ashita-ai.github.io/tessera-python
Project-URL: Repository, https://github.com/ashita-ai/tessera-python
Project-URL: Tessera Server, https://github.com/ashita-ai/tessera
Author: Tessera Team
License: MIT
License-File: LICENSE
Keywords: data-contracts,data-engineering,schema,tessera
Classifier: Development Status :: 4 - Beta
Classifier: Intended Audience :: Developers
Classifier: License :: OSI Approved :: MIT License
Classifier: Programming Language :: Python :: 3
Classifier: Programming Language :: Python :: 3.10
Classifier: Programming Language :: Python :: 3.11
Classifier: Programming Language :: Python :: 3.12
Classifier: Programming Language :: Python :: 3.13
Classifier: Topic :: Software Development :: Libraries :: Python Modules
Classifier: Typing :: Typed
Requires-Python: >=3.10
Requires-Dist: httpx>=0.25.0
Requires-Dist: pydantic>=2.0.0
Provides-Extra: dev
Requires-Dist: mypy>=1.0.0; extra == 'dev'
Requires-Dist: pre-commit>=3.0.0; extra == 'dev'
Requires-Dist: pytest-asyncio>=0.21.0; extra == 'dev'
Requires-Dist: pytest-httpx>=0.21.0; extra == 'dev'
Requires-Dist: pytest>=7.0.0; extra == 'dev'
Requires-Dist: ruff>=0.8.0; extra == 'dev'
